BlaBlaCar_API-0.2.3.dist-info/LICENSE.txt
BlaBlaCar_API-0.2.3.dist-info/METADATA
BlaBlaCar_API-0.2.3.dist-info/RECORD
BlaBlaCar_API-0.2.3.dist-info/WHEEL
BlaBlaCar_API-0.2.3.dist-info/top_level.txt
blablacarapi/__init__.py
blablacarapi/api_exceptions.py
blablacarapi/bind.py
blablacarapi/client.py
blablacarapi/debug.py
blablacarapi/models.py
blablacarapi/paging.py
