Metadata-Version: 2.1
Name: BlaBlaCar-API
Version: 0.2.3
Summary: BlaBlaCar Client Api
Home-page: https://github.com/arrrlo/BlaBlaCar-Client-Api
Author: Ivan Arar
Author-email: ivan.arar@gmail.com
License: MIT
Project-URL: Source, https://github.com/arrrlo/BlaBlaCar-Client-Api
Keywords: blablacar,api,trip,distance
Platform: UNKNOWN
Classifier: Development Status :: 4 - Beta
Classifier: Intended Audience :: Developers
Classifier: Topic :: Software Development :: Build Tools
Classifier: License :: OSI Approved :: MIT License
Classifier: Programming Language :: Python :: 2.7
Classifier: Programming Language :: Python :: 3.6
Requires-Dist: requests (~=2.20.0)
Requires-Dist: click (~=6.7)
Requires-Dist: colorama (~=0.3)
